{
	"configurations" : 
	[
		{
			"directories" : 
			[
				{
					"build" : ".",
					"jsonFile" : "directory-.-Debug-d0094a50bb2071803777.json",
					"minimumCMakeVersion" : 
					{
						"string" : "3.26"
					},
					"projectIndex" : 0,
					"source" : ".",
					"targetIndexes" : 
					[
						0
					]
				}
			],
			"name" : "Debug",
			"projects" : 
			[
				{
					"directoryIndexes" : 
					[
						0
					],
					"name" : "UdemyStuff2",
					"targetIndexes" : 
					[
						0
					]
				}
			],
			"targets" : 
			[
				{
					"directoryIndex" : 0,
					"id" : "UdemyStuff2::@6890427a1f51a3e7e1df",
					"jsonFile" : "target-UdemyStuff2-Debug-fe99c430063ae23cbab6.json",
					"name" : "UdemyStuff2",
					"projectIndex" : 0
				}
			]
		}
	],
	"kind" : "codemodel",
	"paths" : 
	{
		"build" : "C:/Users/marka/Documents/CSC-344-HW/UdemyStuff/UdemyStuff2/cmake-build-debug",
		"source" : "C:/Users/marka/Documents/CSC-344-HW/UdemyStuff/UdemyStuff2"
	},
	"version" : 
	{
		"major" : 2,
		"minor" : 5
	}
}
